evtxtoelk/__init__.py
evtxtoelk-1.0.2.dist-info/METADATA
evtxtoelk-1.0.2.dist-info/RECORD
evtxtoelk-1.0.2.dist-info/WHEEL
evtxtoelk-1.0.2.dist-info/top_level.txt
