Metadata-Version: 2.1
Name: evtxtoelk
Version: 1.0.2
Summary: A lightweight tool to load Windows Event Log evtx files into Elasticsearch.
Home-page: https://github.com/dgunter/evtxtoelk
Author: Dan Gunter
Author-email: dangunter@gmail.com
License: UNKNOWN
Download-URL: https://github.com/dgunter/evtxtoelk/archive/v1.0.2.tar.gz
Keywords: InfoSec,Windows Event Logs,Elasticsearch,security
Platform: UNKNOWN
Classifier: Programming Language :: Python :: 3
Classifier: License :: OSI Approved :: MIT License
Classifier: Operating System :: OS Independent
Classifier: Topic :: Security
Requires-Dist: python-evtx
Requires-Dist: elasticsearch
Requires-Dist: xmltodict
